{
  "parameters": {
    "N_particles": 60,
    "box": 1.0,
    "radius": 0.022,
    "dt": 0.01,
    "epsilon": 1e-08,
    "N_forward": 400,
    "N_reverse": 200,
    "seed": 137
  },
  "lyapunov": {
    "lambda_per_step": 0.11048455,
    "lambda_rev_per_step": -3.835e-05,
    "fit_intercept": -19.74175096,
    "fit_n_points": 169,
    "doubling_time_steps": 6.274,
    "t_macro_steps": 166.726
  },
  "forward_phase": [
    {
      "step": 0,
      "delta": 1e-08,
      "log_delta": -18.42068074
    },
    {
      "step": 10,
      "delta": 1.91e-08,
      "log_delta": -17.77583992
    },
    {
      "step": 20,
      "delta": 1.93e-08,
      "log_delta": -17.76575452
    },
    {
      "step": 30,
      "delta": 2.18e-08,
      "log_delta": -17.64149075
    },
    {
      "step": 40,
      "delta": 2.781e-07,
      "log_delta": -15.09524003
    },
    {
      "step": 50,
      "delta": 4.799e-07,
      "log_delta": -14.54968744
    },
    {
      "step": 60,
      "delta": 1.0666e-06,
      "log_delta": -13.7510799
    },
    {
      "step": 70,
      "delta": 5.6356e-06,
      "log_delta": -12.08640947
    },
    {
      "step": 80,
      "delta": 1.17539e-05,
      "log_delta": -11.35132505
    },
    {
      "step": 90,
      "delta": 0.0001331674,
      "log_delta": -8.92390357
    },
    {
      "step": 100,
      "delta": 0.0002914983,
      "log_delta": -8.14047651
    },
    {
      "step": 110,
      "delta": 0.0005162725,
      "log_delta": -7.56887575
    },
    {
      "step": 120,
      "delta": 0.0007775361,
      "log_delta": -7.15938054
    },
    {
      "step": 130,
      "delta": 0.0062466704,
      "log_delta": -5.0757067
    },
    {
      "step": 140,
      "delta": 0.0213722553,
      "log_delta": -3.84566168
    },
    {
      "step": 150,
      "delta": 0.0455331873,
      "log_delta": -3.08931383
    },
    {
      "step": 160,
      "delta": 0.0627353132,
      "log_delta": -2.76883078
    },
    {
      "step": 170,
      "delta": 0.4709438218,
      "log_delta": -0.75301647
    },
    {
      "step": 180,
      "delta": 2.1011689185,
      "log_delta": 0.74249382
    },
    {
      "step": 190,
      "delta": 3.0360847986,
      "log_delta": 1.11056879
    },
    {
      "step": 200,
      "delta": 5.2085987774,
      "log_delta": 1.65031087
    },
    {
      "step": 210,
      "delta": 5.9742566856,
      "log_delta": 1.78745969
    },
    {
      "step": 220,
      "delta": 6.7762719877,
      "log_delta": 1.9134271
    },
    {
      "step": 230,
      "delta": 6.9242149742,
      "log_delta": 1.93502468
    },
    {
      "step": 240,
      "delta": 7.0592584541,
      "log_delta": 1.95434001
    },
    {
      "step": 250,
      "delta": 7.1025757663,
      "log_delta": 1.9604575
    },
    {
      "step": 260,
      "delta": 6.8215310987,
      "log_delta": 1.92008395
    },
    {
      "step": 270,
      "delta": 7.3914923031,
      "log_delta": 2.00032965
    },
    {
      "step": 280,
      "delta": 7.5675353579,
      "log_delta": 2.02386743
    },
    {
      "step": 290,
      "delta": 7.6677547391,
      "log_delta": 2.03702384
    },
    {
      "step": 300,
      "delta": 8.1198383662,
      "log_delta": 2.09431025
    },
    {
      "step": 310,
      "delta": 7.8506596572,
      "log_delta": 2.06059756
    },
    {
      "step": 320,
      "delta": 8.1119225319,
      "log_delta": 2.0933349
    },
    {
      "step": 330,
      "delta": 8.3575901405,
      "log_delta": 2.12317012
    },
    {
      "step": 340,
      "delta": 7.8532735137,
      "log_delta": 2.06093045
    },
    {
      "step": 350,
      "delta": 7.8858739132,
      "log_delta": 2.06507305
    },
    {
      "step": 360,
      "delta": 7.7931620021,
      "log_delta": 2.05324668
    },
    {
      "step": 370,
      "delta": 8.3321525981,
      "log_delta": 2.12012184
    },
    {
      "step": 380,
      "delta": 8.1331335232,
      "log_delta": 2.09594628
    },
    {
      "step": 390,
      "delta": 8.068069281,
      "log_delta": 2.08791421
    },
    {
      "step": 400,
      "delta": 8.13305071,
      "log_delta": 2.09593609
    }
  ],
  "reversal_phase": [
    {
      "step": 0,
      "delta": 8.13305071,
      "log_delta": 2.09593609
    },
    {
      "step": 10,
      "delta": 8.0102932424,
      "log_delta": 2.08072737
    },
    {
      "step": 20,
      "delta": 7.4737311102,
      "log_delta": 2.01139435
    },
    {
      "step": 30,
      "delta": 8.0291970525,
      "log_delta": 2.08308453
    },
    {
      "step": 40,
      "delta": 7.5848306045,
      "log_delta": 2.02615028
    },
    {
      "step": 50,
      "delta": 7.7470631034,
      "log_delta": 2.04731382
    },
    {
      "step": 60,
      "delta": 7.5895406919,
      "log_delta": 2.02677107
    },
    {
      "step": 70,
      "delta": 7.3961323251,
      "log_delta": 2.0009572
    },
    {
      "step": 80,
      "delta": 7.5970284233,
      "log_delta": 2.02775717
    },
    {
      "step": 90,
      "delta": 7.9718071699,
      "log_delta": 2.07591121
    },
    {
      "step": 100,
      "delta": 7.6382488975,
      "log_delta": 2.03316838
    },
    {
      "step": 110,
      "delta": 7.7813519336,
      "log_delta": 2.05173009
    },
    {
      "step": 120,
      "delta": 7.6706080506,
      "log_delta": 2.03739589
    },
    {
      "step": 130,
      "delta": 8.3152977382,
      "log_delta": 2.11809692
    },
    {
      "step": 140,
      "delta": 7.7374198741,
      "log_delta": 2.04606828
    },
    {
      "step": 150,
      "delta": 7.3950949731,
      "log_delta": 2.00081694
    },
    {
      "step": 160,
      "delta": 7.3584502156,
      "log_delta": 1.99584934
    },
    {
      "step": 170,
      "delta": 7.8886265301,
      "log_delta": 2.06542204
    },
    {
      "step": 180,
      "delta": 7.9470327945,
      "log_delta": 2.07279863
    },
    {
      "step": 190,
      "delta": 7.8169282553,
      "log_delta": 2.05629167
    },
    {
      "step": 200,
      "delta": 7.6874205797,
      "log_delta": 2.0395853
    }
  ]
}